[{"type":"mousemove","pageX":524,"pageY":1},{"type":"mousemove","pageX":537,"pageY":20},{"type":"mousemove","pageX":548,"pageY":32},{"type":"mousemove","pageX":567,"pageY":50},{"type":"mousemove","pageX":598,"pageY":70},{"type":"mousemove","pageX":634,"pageY":95},{"type":"mousemove","pageX":646,"pageY":106},{"type":"mousemove","pageX":665,"pageY":130},{"type":"mousemove","pageX":669,"pageY":136},{"type":"mousemove","pageX":671,"pageY":146},{"type":"mousemove","pageX":672,"pageY":149},{"type":"mousemove","pageX":672,"pageY":152},{"type":"mousemove","pageX":672,"pageY":162},{"type":"mousemove","pageX":674,"pageY":187},{"type":"mousemove","pageX":674,"pageY":198},{"type":"mousemove","pageX":674,"pageY":233},{"type":"mousemove","pageX":678,"pageY":252},{"type":"mousemove","pageX":678,"pageY":271},{"type":"mousemove","pageX":678,"pageY":291},{"type":"mousemove","pageX":678,"pageY":310},{"type":"mousemove","pageX":679,"pageY":326},{"type":"mousemove","pageX":680,"pageY":337},{"type":"mousemove","pageX":680,"pageY":343},{"type":"mousemove","pageX":669,"pageY":385},{"type":"mousemove","pageX":658,"pageY":408},{"type":"mousemove","pageX":646,"pageY":425},{"type":"mousemove","pageX":640,"pageY":431},{"type":"mousemove","pageX":640,"pageY":432},{"type":"mousemove","pageX":639,"pageY":432},{"type":"mousemove","pageX":641,"pageY":435},{"type":"mousemove","pageX":640,"pageY":436},{"type":"mousemove","pageX":640,"pageY":437},{"type":"mousemove","pageX":640,"pageY":440},{"type":"mousemove","pageX":639,"pageY":441},{"type":"mousemove","pageX":638,"pageY":443},{"type":"mousemove","pageX":638,"pageY":449},{"type":"mousemove","pageX":636,"pageY":455},{"type":"mousemove","pageX":636,"pageY":459},{"type":"mousemove","pageX":635,"pageY":465},{"type":"mousemove","pageX":634,"pageY":467},{"type":"mousemove","pageX":633,"pageY":475},{"type":"mousemove","pageX":633,"pageY":477},{"type":"mousemove","pageX":632,"pageY":478},{"type":"mousemove","pageX":631,"pageY":479},{"type":"mousemove","pageX":630,"pageY":479},{"type":"mousemove","pageX":629,"pageY":479},{"type":"mousemove","pageX":628,"pageY":479},{"type":"mousemove","pageX":627,"pageY":479},{"type":"mousemove","pageX":626,"pageY":479},{"type":"mousemove","pageX":625,"pageY":480},{"type":"mousemove","pageX":616,"pageY":484},{"type":"mousemove","pageX":603,"pageY":491},{"type":"mousemove","pageX":590,"pageY":499},{"type":"mousemove","pageX":578,"pageY":506},{"type":"mousemove","pageX":568,"pageY":511},{"type":"mousemove","pageX":561,"pageY":516},{"type":"mousemove","pageX":558,"pageY":519},{"type":"mousemove","pageX":545,"pageY":526},{"type":"mousemove","pageX":525,"pageY":537},{"type":"mousemove","pageX":513,"pageY":546},{"type":"mousemove","pageX":499,"pageY":553},{"type":"mousemove","pageX":487,"pageY":560},{"type":"mousemove","pageX":477,"pageY":568},{"type":"mousemove","pageX":474,"pageY":569},{"type":"mousemove","pageX":465,"pageY":574},{"type":"mousemove","pageX":454,"pageY":581},{"type":"mousemove","pageX":436,"pageY":589},{"type":"mousemove","pageX":416,"pageY":593},{"type":"mousemove","pageX":395,"pageY":599},{"type":"mousemove","pageX":373,"pageY":602},{"type":"mousemove","pageX":369,"pageY":603},{"type":"mousemove","pageX":368,"pageY":604},{"type":"mousemove","pageX":367,"pageY":604},{"type":"mousemove","pageX":366,"pageY":604},{"type":"mousemove","pageX":363,"pageY":605},{"type":"mousemove","pageX":359,"pageY":607},{"type":"mousemove","pageX":353,"pageY":610},{"type":"mousemove","pageX":343,"pageY":618},{"type":"mousemove","pageX":337,"pageY":622},{"type":"mousemove","pageX":309,"pageY":619},{"type":"mousemove","pageX":286,"pageY":580},{"type":"mousemove","pageX":264,"pageY":531},{"type":"mousemove","pageX":248,"pageY":474},{"type":"mousemove","pageX":226,"pageY":398},{"type":"mousemove","pageX":197,"pageY":279},{"type":"mousemove","pageX":181,"pageY":246},{"type":"mousemove","pageX":164,"pageY":219},{"type":"mousemove","pageX":104,"pageY":129},{"type":"mousemove","pageX":93,"pageY":112},{"type":"mousemove","pageX":86,"pageY":95},{"type":"mousemove","pageX":84,"pageY":77},{"type":"mousemove","pageX":77,"pageY":54},{"type":"mousemove","pageX":75,"pageY":39},{"type":"mousemove","pageX":74,"pageY":32},{"type":"stop","pageX":"","pageY":""},{"type":"mousemove","pageX":73,"pageY":24},{"type":"mousemove","pageX":73,"pageY":21},{"type":"mousemove","pageX":73,"pageY":18},{"type":"mousemove","pageX":74,"pageY":13},{"type":"mousemove","pageX":75,"pageY":8},{"type":"mousemove","pageX":77,"pageY":3},{"type":"mousemove","pageX":77,"pageY":1},{"type":"stop","pageX":"","pageY":""},{"type":"stop","pageX":"","pageY":""},{"type":"stop","pageX":"","pageY":""},{"type":"stop","pageX":"","pageY":""},{"type":"stop","pageX":"","pageY":""},{"type":"stop","pageX":"","pageY":""},{"type":"stop","pageX":"","pageY":""},{"type":"stop","pageX":"","pageY":""},{"type":"stop","pageX":"","pageY":""},{"type":"stop","pageX":"","pageY":""},{"type":"stop","pageX":"","pageY":""},{"type":"stop","pageX":"","pageY":""},{"type":"stop","pageX":"","pageY":""},{"type":"stop","pageX":"","pageY":""},{"type":"stop","pageX":"","pageY":""},{"type":"stop","pageX":"","pageY":""},{"type":"stop","pageX":"","pageY":""},{"type":"stop","pageX":"","pageY":""},{"type":"stop","pageX":"","pageY":""},{"type":"stop","pageX":"","pageY":""},{"type":"stop","pageX":"","pageY":""},{"type":"stop","pageX":"","pageY":""},{"type":"stop","pageX":"","pageY":""},{"type":"stop","pageX":"","pageY":""},{"type":"stop","pageX":"","pageY":""},{"type":"stop","pageX":"","pageY":""},{"type":"stop","pageX":"","pageY":""},{"type":"stop","pageX":"","pageY":""}]